kahi_wikipedia_affiliations/Kahi_wikipedia_affiliations.py
kahi_wikipedia_affiliations/__init__.py
kahi_wikipedia_affiliations/_version.py
Kahi_wikipedia_affiliations-0.1.0b0.dist-info/LICENSE
Kahi_wikipedia_affiliations-0.1.0b0.dist-info/METADATA
Kahi_wikipedia_affiliations-0.1.0b0.dist-info/WHEEL
Kahi_wikipedia_affiliations-0.1.0b0.dist-info/top_level.txt
Kahi_wikipedia_affiliations-0.1.0b0.dist-info/RECORD
